integer_lang/__init__.py
integer_lang/__main__.py
integer_lang/basenum.py
integer_lang/standalone.py
integer_lang-1.3.0.dist-info/LICENSE
integer_lang-1.3.0.dist-info/METADATA
integer_lang-1.3.0.dist-info/WHEEL
integer_lang-1.3.0.dist-info/top_level.txt
integer_lang-1.3.0.dist-info/RECORD
